ffmpeg_streaming/__init__.py
ffmpeg_streaming/_clouds.py
ffmpeg_streaming/_command_builder.py
ffmpeg_streaming/_format.py
ffmpeg_streaming/_hls_helper.py
ffmpeg_streaming/_input.py
ffmpeg_streaming/_media.py
ffmpeg_streaming/_media_property.py
ffmpeg_streaming/_process.py
ffmpeg_streaming/_reperesentation.py
ffmpeg_streaming/_utiles.py
ffmpeg_streaming/ffprobe.py
ffmpeg_streaming/tests/__init__.py
ffmpeg_streaming/tests/test_ffmpeg_video_streaming.py
python_ffmpeg_video_streaming-0.1.16.dist-info/LICENSE
python_ffmpeg_video_streaming-0.1.16.dist-info/METADATA
python_ffmpeg_video_streaming-0.1.16.dist-info/WHEEL
python_ffmpeg_video_streaming-0.1.16.dist-info/top_level.txt
python_ffmpeg_video_streaming-0.1.16.dist-info/RECORD
