Metadata-Version: 2.1
Name: python-ffmpeg-video-streaming
Version: 0.1.16
Summary: Package media content for online streaming(DASH and HLS) using ffmpeg
Home-page: https://github.com/quasarstream/python-ffmpeg-video-streaming
Author: Amin Yazdanpanah
Author-email: contact@aminyazdanpanah.com
Project-URL: Bug Tracker, https://github.com/quasarstream/python-ffmpeg-video-streaming/issues
Project-URL: Documentation, https://quasarstream.com/op/python/ffmpeg-streaming/
Project-URL: Source Code, https://github.com/quasarstream/python-ffmpeg-video-streaming
Classifier: Programming Language :: Python :: 3.8
Classifier: Programming Language :: Python :: 3.9
Classifier: Programming Language :: Python :: 3.10
Classifier: Programming Language :: Python :: 3.11
Classifier: License :: OSI Approved :: MIT License
Classifier: Operating System :: OS Independent
Requires-Python: >=3.8
License-File: LICENSE
